LICENSE
MANIFEST.in
README.rst
setup.py
django_markdown_editor.egg-info/PKG-INFO
django_markdown_editor.egg-info/SOURCES.txt
django_markdown_editor.egg-info/dependency_links.txt
django_markdown_editor.egg-info/top_level.txt
markdown_editor/__init__.py
markdown_editor/admin.py
markdown_editor/apps.py
markdown_editor/forms.py
markdown_editor/models.py
markdown_editor/settings.py
markdown_editor/tests.py
markdown_editor/urls.py
markdown_editor/utils.py
markdown_editor/views.py
markdown_editor/widgets.py
markdown_editor/migrations/__init__.py
markdown_editor/static/markdown_editor/test.html
markdown_editor/static/markdown_editor/css/editormd.css
markdown_editor/static/markdown_editor/css/editormd.logo.css
markdown_editor/static/markdown_editor/css/editormd.logo.min.css
markdown_editor/static/markdown_editor/css/editormd.min.css
markdown_editor/static/markdown_editor/css/editormd.preview.css
markdown_editor/static/markdown_editor/css/editormd.preview.min.css
markdown_editor/static/markdown_editor/fonts/FontAwesome.otf
markdown_editor/static/markdown_editor/fonts/editormd-logo.eot
markdown_editor/static/markdown_editor/fonts/editormd-logo.svg
markdown_editor/static/markdown_editor/fonts/editormd-logo.ttf
markdown_editor/static/markdown_editor/fonts/editormd-logo.woff
markdown_editor/static/markdown_editor/fonts/fontawesome-webfont.eot
markdown_editor/static/markdown_editor/fonts/fontawesome-webfont.svg
markdown_editor/static/markdown_editor/fonts/fontawesome-webfont.ttf
markdown_editor/static/markdown_editor/fonts/fontawesome-webfont.woff
markdown_editor/static/markdown_editor/fonts/fontawesome-webfont.woff2
markdown_editor/static/markdown_editor/images/loading.gif
markdown_editor/static/markdown_editor/images/loading@2x.gif
markdown_editor/static/markdown_editor/images/loading@3x.gif
markdown_editor/static/markdown_editor/images/logos/editormd-favicon-16x16.ico
markdown_editor/static/markdown_editor/images/logos/editormd-favicon-24x24.ico
markdown_editor/static/markdown_editor/images/logos/editormd-favicon-32x32.ico
markdown_editor/static/markdown_editor/images/logos/editormd-favicon-48x48.ico
